notetypecho/__init__.py
notetypecho/log.py
notetypecho/main.py
notetypecho/models.py
notetypecho/core/__init__.py
notetypecho/core/core.py
notetypecho/core/entry.py
notetypecho/core/log.py
notetypecho/publish/__init__.py
notetypecho/publish/core.py
notetypecho-0.1.10.dist-info/METADATA
notetypecho-0.1.10.dist-info/WHEEL
notetypecho-0.1.10.dist-info/top_level.txt
notetypecho-0.1.10.dist-info/RECORD
