Metadata-Version: 2.1
Name: notetypecho
Version: 0.1.10
Summary: notetypecho
Home-page: https://github.com/1007530194
Author: euler
Author-email: 1007530194@qq.com
License: UNKNOWN
Platform: UNKNOWN
Requires-Dist: notetool
